wtphm/__init__.py
wtphm/batch.py
wtphm/pred_processing.py
wtphm/clustering/__init__.py
wtphm/clustering/batch_clustering.py
wtphm/clustering/event_probs.py
wtphm-0.1.3.dist-info/LICENSE.txt
wtphm-0.1.3.dist-info/METADATA
wtphm-0.1.3.dist-info/WHEEL
wtphm-0.1.3.dist-info/top_level.txt
wtphm-0.1.3.dist-info/RECORD
