Metadata-Version: 2.1
Name: wtphm
Version: 0.1.3
Summary: SCADA data pre-processing library for prognostics and healthmanagement and fault detection of wind turbines
Home-page: https://github.com/lkev/wtphm
Author: Kevin Leahy
License: UNKNOWN
Platform: UNKNOWN
Classifier: Programming Language :: Python :: 3
Classifier: License :: OSI Approved :: GNU General Public License v3 (GPLv3)
Classifier: Operating System :: OS Independent
Requires-Python: >=3.6
Requires-Dist: pandas
Requires-Dist: numpy
Requires-Dist: scipy
Requires-Dist: matplotlib
Requires-Dist: sklearn
